gritic/__init__.py
gritic/dataloader.py
gritic/distributiontools.py
gritic/gritictimer.py
gritic/hitandrun.py
gritic/multiplicityoptimiser.py
gritic/posteriortablegen.py
gritic/route_tree.py
gritic/sampletools.py
gritic/timingranges.py
gritic/treegenerator.py
gritic/treetools.py
gritic-0.0.8.dist-info/licenses/LICENSE
gritic-0.0.8.dist-info/METADATA
gritic-0.0.8.dist-info/WHEEL
gritic-0.0.8.dist-info/top_level.txt
gritic-0.0.8.dist-info/RECORD
