Metadata-Version: 2.4
Name: gritic
Version: 0.0.8
Summary: A module to time complex copy number gains in cancer genomes
Home-page: https://github.com/VanLoo-lab/gritic
Download-URL: https://github.com/VanLoo-lab/gritic/archive/refs/tags/v0.0.8.tar.gz
Author: Toby Baker
Author-email: tobybaker@mednet.ucla.edu
Maintainer: Toby Baker
Maintainer-email: tobybaker@mednet.ucla.edu
License: GNU AFFERO GENERAL PUBLIC LICENSE Version 3
Classifier: Programming Language :: Python :: 3
Classifier: License :: OSI Approved :: GNU Affero General Public License v3
Classifier: Operating System :: OS Independent
License-File: LICENSE
Requires-Dist: numpy
Requires-Dist: pandas
Requires-Dist: matplotlib
Requires-Dist: scipy
Requires-Dist: scikit-learn
Requires-Dist: networkx
Requires-Dist: numba
Dynamic: author
Dynamic: author-email
Dynamic: classifier
Dynamic: description
Dynamic: description-content-type
Dynamic: download-url
Dynamic: home-page
Dynamic: license
Dynamic: license-file
Dynamic: maintainer
Dynamic: maintainer-email
Dynamic: requires-dist
Dynamic: summary
